optics_design_workbench/__init__.py
optics_design_workbench/detect_pyside.py
optics_design_workbench/init_gui.py
optics_design_workbench/io.py
optics_design_workbench/timing.py
optics_design_workbench/distributions/__init__.py
optics_design_workbench/distributions/points_by_density.py
optics_design_workbench/distributions/random_number_generator.py
optics_design_workbench/freecad_elements/__init__.py
optics_design_workbench/freecad_elements/common.py
optics_design_workbench/freecad_elements/find.py
optics_design_workbench/freecad_elements/generic_source.py
optics_design_workbench/freecad_elements/optical_group.py
optics_design_workbench/freecad_elements/point_source.py
optics_design_workbench/freecad_elements/ray.py
optics_design_workbench/freecad_elements/replay_source.py
optics_design_workbench/freecad_elements/simulation_actions.py
optics_design_workbench/freecad_elements/simulation_settings.py
optics_design_workbench/freecad_elements/surface_source.py
optics_design_workbench/gui_windows/__init__.py
optics_design_workbench/gui_windows/common.py
optics_design_workbench/gui_windows/progress.py
optics_design_workbench/icons/absorber.svg
optics_design_workbench/icons/add-absorber.svg
optics_design_workbench/icons/add-grating.svg
optics_design_workbench/icons/add-lens.svg
optics_design_workbench/icons/add-mirror.svg
optics_design_workbench/icons/add-pointsource.svg
optics_design_workbench/icons/add-replaysource.svg
optics_design_workbench/icons/add-settings.svg
optics_design_workbench/icons/add-surfacesource.svg
optics_design_workbench/icons/add-vacuum.svg
optics_design_workbench/icons/clear.svg
optics_design_workbench/icons/fans.svg
optics_design_workbench/icons/grating.svg
optics_design_workbench/icons/lens.svg
optics_design_workbench/icons/mirror.svg
optics_design_workbench/icons/pointsource.svg
optics_design_workbench/icons/pseudo.svg
optics_design_workbench/icons/reload.svg
optics_design_workbench/icons/replaysource.svg
optics_design_workbench-0.7.0.dist-info/METADATA
optics_design_workbench-0.7.0.dist-info/WHEEL
optics_design_workbench-0.7.0.dist-info/licenses/LICENSE.txt
optics_design_workbench-0.7.0.dist-info/RECORD
