Metadata-Version: 2.4
Name: optics_design_workbench
Version: 0.7.0
Summary: Physically accurate forward ray tracing for optics simulation and optimization with FreeCAD workbench frontend inspired by the FreeCAD OpticsWorkbench
Project-URL: Homepage, https://github.com/zaphB/freecad.optics_design_workbench
Project-URL: Repository, https://github.com/zaphB/freecad.optics_design_workbench.git
Author-email: Philipp Bredol <philipp.bredol@rwth-aachen.de>
License: 
License-File: LICENSE.txt
Requires-Python: >=3.11
Requires-Dist: atomicwrites
Requires-Dist: cloudpickle
Requires-Dist: jupyterlab
Requires-Dist: matplotlib
Requires-Dist: numpy>1.24.4
Requires-Dist: pyside6
Requires-Dist: scipy>=1.14.0
Requires-Dist: seaborn
Requires-Dist: sympy
